odoo/addons/pos_event_sale_registration_qr_code/README.rst
odoo/addons/pos_event_sale_registration_qr_code/__init__.py
odoo/addons/pos_event_sale_registration_qr_code/__manifest__.py
odoo/addons/pos_event_sale_registration_qr_code/i18n/es.po
odoo/addons/pos_event_sale_registration_qr_code/i18n/it.po
odoo/addons/pos_event_sale_registration_qr_code/i18n/pos_event_sale_registration_qr_code.pot
odoo/addons/pos_event_sale_registration_qr_code/readme/CONTRIBUTORS.rst
odoo/addons/pos_event_sale_registration_qr_code/readme/DESCRIPTION.rst
odoo/addons/pos_event_sale_registration_qr_code/static/description/icon.png
odoo/addons/pos_event_sale_registration_qr_code/static/description/index.html
odoo/addons/pos_event_sale_registration_qr_code/static/src/xml/EventRegistrationReceipt.xml
odoo_addon_pos_event_sale_registration_qr_code-15.0.1.0.0.10.dist-info/METADATA
odoo_addon_pos_event_sale_registration_qr_code-15.0.1.0.0.10.dist-info/WHEEL
odoo_addon_pos_event_sale_registration_qr_code-15.0.1.0.0.10.dist-info/top_level.txt
odoo_addon_pos_event_sale_registration_qr_code-15.0.1.0.0.10.dist-info/RECORD
